bee_taxonomy/__init__.py
bee_taxonomy/taxonomy.py
bee_taxonomy/utils.py
bee_taxonomy-0.0.15.dist-info/METADATA
bee_taxonomy-0.0.15.dist-info/WHEEL
bee_taxonomy-0.0.15.dist-info/licenses/LICENSE
bee_taxonomy-0.0.15.dist-info/RECORD
