Metadata-Version: 2.4
Name: bee-taxonomy
Version: 0.0.15
Summary: A library for taxonomy management.
Project-URL: Homepage, https://github.com/Davidoff2103/taxonomy-lib
Author-email: David Blanco Bautista <davidoff.d777@gmail.com>
License-Expression: MIT
License-File: LICENSE
Classifier: Operating System :: OS Independent
Classifier: Programming Language :: Python :: 3
Requires-Python: >=3.9
Requires-Dist: googlesearch-python==1.3.0
Requires-Dist: langchain-community==0.3.27
Requires-Dist: langchain-huggingface==0.3.1
Requires-Dist: openai==1.101.0
Requires-Dist: python-dotenv==1.1.1
